[{"user":{"rating":"1047","handle":"flowermoon","country":"China","countryFlag":"/i/cn-flag.png","avatar":""},"registrationDate":"3-31-2021","submissions":"0","language":"","scoreRank":"","points":""},
{"user":{"rating":"1142","handle":"rasyidridha","country":"Indonesia","countryFlag":"/i/id-flag.png","avatar":""},"registrationDate":"3-31-2021","submissions":"0","language":"","scoreRank":"","points":""},
{"user":{"rating":"2045","handle":"walrus71","country":"Hungary","countryFlag":"/i/hu-flag.png","avatar":"https://topcoder-prod-media.s3.amazonaws.com/member/profile/walrus71-1469173572220.jpeg"},"registrationDate":"3-31-2021","submissions":"0","language":"","scoreRank":"","points":""},
{"user":{"rating":"870","handle":"babybuffalo","country":"Viet Nam","countryFlag":"/i/vn-flag.png","avatar":""},"registrationDate":"3-31-2021","submissions":"0","language":"","scoreRank":"","points":""},
{"user":{"rating":"739","handle":"pauli89","country":"India","countryFlag":"/i/in-flag.png","avatar":""},"registrationDate":"3-31-2021","submissions":"0","language":"","scoreRank":"","points":""},
{"user":{"rating":"","handle":"adityaarya769","country":"India","countryFlag":"/i/in-flag.png","avatar":""},"registrationDate":"3-31-2021","submissions":"0","language":"","scoreRank":"","points":""},
{"user":{"rating":"990","handle":"thothling","country":"China","countryFlag":"/i/cn-flag.png","avatar":""},"registrationDate":"3-31-2021","submissions":"0","language":"","scoreRank":"","points":""},
{"user":{"rating":"619","handle":"Kmande","country":"India","countryFlag":"/i/in-flag.png","avatar":""},"registrationDate":"3-31-2021","submissions":"0","language":"","scoreRank":"","points":""},
{"user":{"rating":"1506","handle":"ap31","country":"Russia","countryFlag":"/i/ru-flag.png","avatar":""},"registrationDate":"3-31-2021","submissions":"0","language":"","scoreRank":"","points":""},
{"user":{"rating":"","handle":"sourabh95","country":"India","countryFlag":"/i/in-flag.png","avatar":""},"registrationDate":"3-31-2021","submissions":"0","language":"","scoreRank":"","points":""},
{"user":{"rating":"1250","handle":"ArijitSinha","country":"India","countryFlag":"/i/in-flag.png","avatar":""},"registrationDate":"3-31-2021","submissions":"0","language":"","scoreRank":"","points":""},
{"user":{"rating":"1555","handle":"kruntuid","country":"Russia","countryFlag":"/i/ru-flag.png","avatar":"https://topcoder-prod-media.s3.amazonaws.com/member/profile/kruntuid-1509057637829.jpeg"},"registrationDate":"3-31-2021","submissions":"0","language":"","scoreRank":"","points":""},
{"user":{"rating":"1281","handle":"dsvolkov","country":"Russia","countryFlag":"/i/ru-flag.png","avatar":""},"registrationDate":"3-31-2021","submissions":"0","language":"","scoreRank":"","points":""},
{"user":{"rating":"1957","handle":"selim_sef","country":"Germany","countryFlag":"/i/de-flag.png","avatar":""},"registrationDate":"3-31-2021","submissions":"459423","language":"","scoreRank":"","points":""},
{"user":{"rating":"","handle":"wcd_ser","country":"Romania","countryFlag":"/i/ro-flag.png","avatar":""},"registrationDate":"3-31-2021","submissions":"0","language":"","scoreRank":"","points":""},
{"user":{"rating":"977","handle":"rtty","country":"Kazakhstan","countryFlag":"/i/kz-flag.png","avatar":""},"registrationDate":"3-31-2021","submissions":"0","language":"","scoreRank":"","points":""},
{"user":{"rating":"1656","handle":"NickDee96","country":"Kenya","countryFlag":"/i/ke-flag.png","avatar":""},"registrationDate":"3-31-2021","submissions":"0","language":"","scoreRank":"","points":""},
{"user":{"rating":"2243","handle":"ika","country":"Georgia","countryFlag":"/i/ge-flag.png","avatar":"https://www.topcoder.com/i/m/ika_big.jpg"},"registrationDate":"3-31-2021","submissions":"0","language":"","scoreRank":"","points":""},
{"user":{"rating":"1095","handle":"tetelias","country":"Russia","countryFlag":"/i/ru-flag.png","avatar":""},"registrationDate":"3-31-2021","submissions":"0","language":"","scoreRank":"","points":""},
{"user":{"rating":"1985","handle":"vdave","country":"Hungary","countryFlag":"/i/hu-flag.png","avatar":"https://www.topcoder.com/i/m/vdave_big.jpg"},"registrationDate":"3-31-2021","submissions":"0","language":"","scoreRank":"","points":""},
{"user":{"rating":"2828","handle":"Psyho","country":"Poland","countryFlag":"/i/pl-flag.png","avatar":"https://www.topcoder.com/i/m/Psyho_big.jpg"},"registrationDate":"3-31-2021","submissions":"0","language":"","scoreRank":"","points":""},
{"user":{"rating":"1299","handle":"a.lowe","country":"Canada","countryFlag":"/i/ca-flag.png","avatar":""},"registrationDate":"3-31-2021","submissions":"459420","language":"","scoreRank":"","points":""},
{"user":{"rating":"","handle":"kriswjma","country":"United States","countryFlag":"/i/us-flag.png","avatar":""},"registrationDate":"3-31-2021","submissions":"0","language":"","scoreRank":"","points":""},
{"user":{"rating":"1921","handle":"ualabs","country":"Russia","countryFlag":"/i/ru-flag.png","avatar":""},"registrationDate":"3-31-2021","submissions":"0","language":"","scoreRank":"","points":""},
{"user":{"rating":"0","handle":"krisjen","country":"United States","countryFlag":"/i/us-flag.png","avatar":""},"registrationDate":"3-31-2021","submissions":"0","language":"","scoreRank":"","points":""},
{"user":{"rating":"1457","handle":"myterisa","country":"United States","countryFlag":"/i/us-flag.png","avatar":"https://www.topcoder.com/i/m/myterisa.jpeg"},"registrationDate":"3-31-2021","submissions":"0","language":"","scoreRank":"","points":""},
{"user":{"rating":"","handle":"mohamed026selmi","country":"Tunisia","countryFlag":"/i/tn-flag.png","avatar":""},"registrationDate":"3-31-2021","submissions":"0","language":"","scoreRank":"","points":""},
{"user":{"rating":"","handle":"cagdas001","country":"Turkey","countryFlag":"/i/tr-flag.png","avatar":""},"registrationDate":"3-31-2021","submissions":"0","language":"","scoreRank":"","points":""},
{"user":{"rating":"1475","handle":"LastEmperor","country":"Russia","countryFlag":"/i/ru-flag.png","avatar":""},"registrationDate":"3-31-2021","submissions":"0","language":"","scoreRank":"","points":""},
{"user":{"rating":"","handle":"shivaprakash9","country":"India","countryFlag":"/i/in-flag.png","avatar":""},"registrationDate":"3-31-2021","submissions":"0","language":"","scoreRank":"","points":""},
{"user":{"rating":"","handle":"settuk","country":"India","countryFlag":"/i/in-flag.png","avatar":""},"registrationDate":"3-31-2021","submissions":"0","language":"","scoreRank":"","points":""},
{"user":{"rating":"952","handle":"mulish","country":"Kenya","countryFlag":"/i/ke-flag.png","avatar":"https://www.topcoder.com/i/m/mulish.jpeg"},"registrationDate":"3-31-2021","submissions":"0","language":"","scoreRank":"","points":""},
{"user":{"rating":"844","handle":"TMALBONPH","country":"Philippines","countryFlag":"/i/ph-flag.png","avatar":"https://www.topcoder.com/i/m/TMALBONPH.png"},"registrationDate":"3-31-2021","submissions":"0","language":"","scoreRank":"","points":""},
{"user":{"rating":"1287","handle":"vparinov","country":"Russia","countryFlag":"/i/ru-flag.png","avatar":""},"registrationDate":"3-31-2021","submissions":"0","language":"","scoreRank":"","points":""},
{"user":{"rating":"973","handle":"codingdrone","country":"India","countryFlag":"/i/in-flag.png","avatar":""},"registrationDate":"3-31-2021","submissions":"0","language":"","scoreRank":"","points":""},
{"user":{"rating":"1270","handle":"cannab","country":"Russia","countryFlag":"/i/ru-flag.png","avatar":"https://topcoder-prod-media.s3.amazonaws.com/member/profile/cannab-1502086409293.jpeg"},"registrationDate":"4-1-2021","submissions":"0","language":"","scoreRank":"","points":""},
{"user":{"rating":"1451","handle":"Vinayaka.Raj","country":"India","countryFlag":"/i/in-flag.png","avatar":""},"registrationDate":"4-1-2021","submissions":"0","language":"","scoreRank":"","points":""},
{"user":{"rating":"655","handle":"Dylan_Liu","country":"China","countryFlag":"/i/cn-flag.png","avatar":""},"registrationDate":"4-1-2021","submissions":"0","language":"","scoreRank":"","points":""},
{"user":{"rating":"","handle":"Dagr","country":"Colombia","countryFlag":"/i/co-flag.png","avatar":""},"registrationDate":"4-1-2021","submissions":"0","language":"","scoreRank":"","points":""},
{"user":{"rating":"","handle":"Lebogang","country":"South Africa","countryFlag":"/i/za-flag.png","avatar":""},"registrationDate":"4-1-2021","submissions":"0","language":"","scoreRank":"","points":""},
{"user":{"rating":"1083","handle":"paolog","country":"Italy","countryFlag":"/i/it-flag.png","avatar":"https://www.topcoder.com/i/m/paolog.jpeg"},"registrationDate":"4-1-2021","submissions":"0","language":"","scoreRank":"","points":""},
{"user":{"rating":"1613","handle":"now_you_see","country":"Russia","countryFlag":"/i/ru-flag.png","avatar":""},"registrationDate":"4-1-2021","submissions":"459015","language":"","scoreRank":"","points":""},
{"user":{"rating":"","handle":"felias","country":"Japan","countryFlag":"/i/jp-flag.png","avatar":""},"registrationDate":"4-1-2021","submissions":"0","language":"","scoreRank":"","points":""},
{"user":{"rating":"1877","handle":"ZFTurbo","country":"Russia","countryFlag":"/i/ru-flag.png","avatar":""},"registrationDate":"4-1-2021","submissions":"0","language":"","scoreRank":"","points":""},
{"user":{"rating":"","handle":"Sjeffry","country":"Russia","countryFlag":"/i/ru-flag.png","avatar":""},"registrationDate":"4-1-2021","submissions":"0","language":"","scoreRank":"","points":""},
{"user":{"rating":"1096","handle":"anshul96go","country":"India","countryFlag":"/i/in-flag.png","avatar":""},"registrationDate":"4-1-2021","submissions":"0","language":"","scoreRank":"","points":""},
{"user":{"rating":"944","handle":"d_a_konovalov","country":"Australia","countryFlag":"/i/au-flag.png","avatar":"https://www.topcoder.com/i/m/d_a_konovalov.jpeg"},"registrationDate":"4-1-2021","submissions":"459710","language":"","scoreRank":"74.22129","points":"74.22129"},
{"user":{"rating":"996","handle":"raytracer1","country":"Algeria","countryFlag":"/i/dz-flag.png","avatar":""},"registrationDate":"4-1-2021","submissions":"0","language":"","scoreRank":"","points":""},
{"user":{"rating":"","handle":"GatMasterD","country":"United States","countryFlag":"/i/us-flag.png","avatar":""},"registrationDate":"4-1-2021","submissions":"456652","language":"","scoreRank":"","points":""},
{"user":{"rating":"","handle":"dereyly","country":"Russia","countryFlag":"/i/ru-flag.png","avatar":""},"registrationDate":"4-1-2021","submissions":"0","language":"","scoreRank":"","points":""},
{"user":{"rating":"681","handle":"marathontester1","country":"United States","countryFlag":"/i/us-flag.png","avatar":""},"registrationDate":"4-1-2021","submissions":"458774","language":"","scoreRank":"50.43124","points":"50.43124"},
{"user":{"rating":"","handle":"Contortionist","country":"Ukraine","countryFlag":"/i/ua-flag.png","avatar":""},"registrationDate":"4-1-2021","submissions":"0","language":"","scoreRank":"","points":""},
{"user":{"rating":"1106","handle":"MaksimovKA","country":"Ukraine","countryFlag":"/i/ua-flag.png","avatar":""},"registrationDate":"4-1-2021","submissions":"0","language":"","scoreRank":"","points":""},
{"user":{"rating":"","handle":"sarahchangzsy","country":"China","countryFlag":"/i/cn-flag.png","avatar":""},"registrationDate":"4-2-2021","submissions":"0","language":"","scoreRank":"","points":""},
{"user":{"rating":"","handle":"prem_kumar27","country":"India","countryFlag":"/i/in-flag.png","avatar":""},"registrationDate":"4-2-2021","submissions":"0","language":"","scoreRank":"","points":""},
{"user":{"rating":"1304","handle":"tongkunvwang","country":"China","countryFlag":"/i/cn-flag.png","avatar":""},"registrationDate":"4-2-2021","submissions":"0","language":"","scoreRank":"","points":""},
{"user":{"rating":"","handle":"ainwonderland","country":"India","countryFlag":"/i/in-flag.png","avatar":""},"registrationDate":"4-2-2021","submissions":"0","language":"","scoreRank":"","points":""},
{"user":{"rating":"","handle":"lxastro0","country":"China","countryFlag":"/i/cn-flag.png","avatar":""},"registrationDate":"4-2-2021","submissions":"459716","language":"","scoreRank":"43.15474","points":"43.15474"},
{"user":{"rating":"646","handle":"dangrz","country":"Poland","countryFlag":"/i/pl-flag.png","avatar":""},"registrationDate":"4-2-2021","submissions":"0","language":"","scoreRank":"","points":""},
{"user":{"rating":"","handle":"akhil08.iitkgp","country":"India","countryFlag":"/i/in-flag.png","avatar":""},"registrationDate":"4-3-2021","submissions":"0","language":"","scoreRank":"","points":""},
{"user":{"rating":"","handle":"sanjaykr7","country":"India","countryFlag":"/i/in-flag.png","avatar":""},"registrationDate":"4-3-2021","submissions":"0","language":"","scoreRank":"","points":""},
{"user":{"rating":"1752","handle":"rekcahd","country":"Russia","countryFlag":"/i/ru-flag.png","avatar":""},"registrationDate":"4-3-2021","submissions":"0","language":"","scoreRank":"","points":""},
{"user":{"rating":"1787","handle":"tcghanareddy","country":"India","countryFlag":"/i/in-flag.png","avatar":""},"registrationDate":"4-3-2021","submissions":"0","language":"","scoreRank":"","points":""},
{"user":{"rating":"","handle":"N41k","country":"India","countryFlag":"/i/in-flag.png","avatar":""},"registrationDate":"4-3-2021","submissions":"0","language":"","scoreRank":"","points":""},
{"user":{"rating":"2191","handle":"mugurelionut","country":"Switzerland","countryFlag":"/i/ch-flag.png","avatar":"https://www.topcoder.com/i/m/mugurelionut.jpeg"},"registrationDate":"4-3-2021","submissions":"0","language":"","scoreRank":"","points":""},
{"user":{"rating":"1669","handle":"nozemigor","country":"Russia","countryFlag":"/i/ru-flag.png","avatar":""},"registrationDate":"4-3-2021","submissions":"0","language":"","scoreRank":"","points":""},
{"user":{"rating":"1047","handle":"waynn","country":"China","countryFlag":"/i/cn-flag.png","avatar":""},"registrationDate":"4-3-2021","submissions":"0","language":"","scoreRank":"","points":""},
{"user":{"rating":"","handle":"mchahhou","country":"Morocco","countryFlag":"/i/ma-flag.png","avatar":""},"registrationDate":"4-4-2021","submissions":"0","language":"","scoreRank":"","points":""},
{"user":{"rating":"1604","handle":"AliGebily","country":"Egypt","countryFlag":"/i/eg-flag.png","avatar":"https://topcoder-prod-media.s3.amazonaws.com/member/profile/AliGebily-1478200321798.jpeg"},"registrationDate":"4-4-2021","submissions":"457436","language":"","scoreRank":"","points":""},
{"user":{"rating":"","handle":"DaniCastro","country":"Spain","countryFlag":"/i/es-flag.png","avatar":""},"registrationDate":"4-4-2021","submissions":"0","language":"","scoreRank":"","points":""},
{"user":{"rating":"869","handle":"irfian_akbar","country":"Indonesia","countryFlag":"/i/id-flag.png","avatar":""},"registrationDate":"4-4-2021","submissions":"0","language":"","scoreRank":"","points":""},
{"user":{"rating":"","handle":"lesh_ghoti","country":"South Africa","countryFlag":"/i/za-flag.png","avatar":""},"registrationDate":"4-4-2021","submissions":"0","language":"","scoreRank":"","points":""},
{"user":{"rating":"0","handle":"dukeprashanth","country":"India","countryFlag":"/i/in-flag.png","avatar":""},"registrationDate":"4-4-2021","submissions":"0","language":"","scoreRank":"","points":""},
{"user":{"rating":"1180","handle":"hotmail","country":"India","countryFlag":"/i/in-flag.png","avatar":""},"registrationDate":"4-4-2021","submissions":"0","language":"","scoreRank":"","points":""},
{"user":{"rating":"","handle":"Pankajvshrma","country":"India","countryFlag":"/i/in-flag.png","avatar":""},"registrationDate":"4-5-2021","submissions":"0","language":"","scoreRank":"","points":""},
{"user":{"rating":"","handle":"Z.paint","country":"China","countryFlag":"/i/cn-flag.png","avatar":""},"registrationDate":"4-5-2021","submissions":"0","language":"","scoreRank":"","points":""},
{"user":{"rating":"2075","handle":"kiminya","country":"Kenya","countryFlag":"/i/ke-flag.png","avatar":""},"registrationDate":"4-5-2021","submissions":"459715","language":"","scoreRank":"68.86339","points":"68.86339"},
{"user":{"rating":"","handle":"pixml","country":"Russia","countryFlag":"/i/ru-flag.png","avatar":""},"registrationDate":"4-5-2021","submissions":"0","language":"","scoreRank":"","points":""},
{"user":{"rating":"1305","handle":"mengue","country":"Brazil","countryFlag":"/i/br-flag.png","avatar":""},"registrationDate":"4-5-2021","submissions":"0","language":"","scoreRank":"","points":""},
{"user":{"rating":"","handle":"BojaVode7973","country":"Japan","countryFlag":"/i/jp-flag.png","avatar":""},"registrationDate":"4-5-2021","submissions":"0","language":"","scoreRank":"","points":""},
{"user":{"rating":"","handle":"PegaZeus","country":"India","countryFlag":"/i/in-flag.png","avatar":""},"registrationDate":"4-5-2021","submissions":"0","language":"","scoreRank":"","points":""},
{"user":{"rating":"","handle":"Jaya_Raj_","country":"India","countryFlag":"/i/in-flag.png","avatar":""},"registrationDate":"4-5-2021","submissions":"0","language":"","scoreRank":"","points":""},
{"user":{"rating":"","handle":"Niveenkh","country":"Palestine, State of","countryFlag":"/i/ps-flag.png","avatar":""},"registrationDate":"4-5-2021","submissions":"0","language":"","scoreRank":"","points":""},
{"user":{"rating":"","handle":"shubh-12","country":"India","countryFlag":"/i/in-flag.png","avatar":""},"registrationDate":"4-5-2021","submissions":"0","language":"","scoreRank":"","points":""},
{"user":{"rating":"","handle":"smgapu","country":"Bangladesh","countryFlag":"/i/bd-flag.png","avatar":""},"registrationDate":"4-5-2021","submissions":"0","language":"","scoreRank":"","points":""},
{"user":{"rating":"","handle":"Rohit484001","country":"India","countryFlag":"/i/in-flag.png","avatar":""},"registrationDate":"4-5-2021","submissions":"0","language":"","scoreRank":"","points":""},
{"user":{"rating":"","handle":"18bcs3772","country":"India","countryFlag":"/i/in-flag.png","avatar":""},"registrationDate":"4-6-2021","submissions":"0","language":"","scoreRank":"","points":""},
{"user":{"rating":"","handle":"nikhilsinghh","country":"India","countryFlag":"/i/in-flag.png","avatar":""},"registrationDate":"4-5-2021","submissions":"0","language":"","scoreRank":"","points":""},
{"user":{"rating":"","handle":"45hw4n1","country":"India","countryFlag":"/i/in-flag.png","avatar":""},"registrationDate":"4-5-2021","submissions":"0","language":"","scoreRank":"","points":""},
{"user":{"rating":"","handle":"gustavo_code18","country":"Mexico","countryFlag":"/i/mx-flag.png","avatar":""},"registrationDate":"4-5-2021","submissions":"0","language":"","scoreRank":"","points":""},
{"user":{"rating":"","handle":"Bigil","country":"India","countryFlag":"/i/in-flag.png","avatar":""},"registrationDate":"4-5-2021","submissions":"0","language":"","scoreRank":"","points":""},
{"user":{"rating":"","handle":"Leonob2019","country":"Colombia","countryFlag":"/i/co-flag.png","avatar":""},"registrationDate":"4-5-2021","submissions":"0","language":"","scoreRank":"","points":""},
{"user":{"rating":"","handle":"Kowshik_01","country":"Bangladesh","countryFlag":"/i/bd-flag.png","avatar":""},"registrationDate":"4-5-2021","submissions":"0","language":"","scoreRank":"","points":""},
{"user":{"rating":"","handle":"viszhnu","country":"India","countryFlag":"/i/in-flag.png","avatar":""},"registrationDate":"4-5-2021","submissions":"0","language":"","scoreRank":"","points":""},
{"user":{"rating":"786","handle":"ZLATKO","country":"Macedonia","countryFlag":"/i/mk-flag.png","avatar":"https://topcoder-prod-media.s3.amazonaws.com/member/profile/ZLATKO-1476657219326.png"},"registrationDate":"4-5-2021","submissions":"0","language":"","scoreRank":"","points":""},
{"user":{"rating":"","handle":"Hardin_Alucard","country":"India","countryFlag":"/i/in-flag.png","avatar":""},"registrationDate":"4-5-2021","submissions":"0","language":"","scoreRank":"","points":""},
{"user":{"rating":"","handle":"lutaiphong","country":"Viet Nam","countryFlag":"/i/vn-flag.png","avatar":""},"registrationDate":"4-5-2021","submissions":"0","language":"","scoreRank":"","points":""},
{"user":{"rating":"","handle":"bayonapro","country":"Spain","countryFlag":"/i/es-flag.png","avatar":""},"registrationDate":"4-5-2021","submissions":"0","language":"","scoreRank":"","points":""},
{"user":{"rating":"1217","handle":"ketzjs09","country":"India","countryFlag":"/i/in-flag.png","avatar":"https://topcoder-prod-media.s3.amazonaws.com/member/profile/ketzjs09-1501871409574.jpeg"},"registrationDate":"4-5-2021","submissions":"0","language":"","scoreRank":"","points":""},
{"user":{"rating":"","handle":"prashant709","country":"India","countryFlag":"/i/in-flag.png","avatar":""},"registrationDate":"4-5-2021","submissions":"0","language":"","scoreRank":"","points":""},
{"user":{"rating":"","handle":"max334","country":"Palestine, State of","countryFlag":"/i/ps-flag.png","avatar":""},"registrationDate":"4-5-2021","submissions":"0","language":"","scoreRank":"","points":""},
{"user":{"rating":"","handle":"SumaHS","country":"United Arab Emirates","countryFlag":"/i/ae-flag.png","avatar":""},"registrationDate":"4-5-2021","submissions":"0","language":"","scoreRank":"","points":""},
{"user":{"rating":"","handle":"rleehj","country":"United States","countryFlag":"/i/us-flag.png","avatar":""},"registrationDate":"4-5-2021","submissions":"0","language":"","scoreRank":"","points":""},
{"user":{"rating":"","handle":"vgaudill","country":"France","countryFlag":"/i/fr-flag.png","avatar":""},"registrationDate":"4-5-2021","submissions":"0","language":"","scoreRank":"","points":""},
{"user":{"rating":"","handle":"arvindgta0704","country":"India","countryFlag":"/i/in-flag.png","avatar":""},"registrationDate":"4-5-2021","submissions":"0","language":"","scoreRank":"","points":""},
{"user":{"rating":"","handle":"ommishra1","country":"India","countryFlag":"/i/in-flag.png","avatar":""},"registrationDate":"4-5-2021","submissions":"0","language":"","scoreRank":"","points":""},
{"user":{"rating":"","handle":"priyansudas2001","country":"India","countryFlag":"/i/in-flag.png","avatar":""},"registrationDate":"4-5-2021","submissions":"0","language":"","scoreRank":"","points":""},
{"user":{"rating":"","handle":"RShellac","country":"India","countryFlag":"/i/in-flag.png","avatar":""},"registrationDate":"4-5-2021","submissions":"0","language":"","scoreRank":"","points":""},
{"user":{"rating":"","handle":"jayant_k7","country":"India","countryFlag":"/i/in-flag.png","avatar":""},"registrationDate":"4-5-2021","submissions":"0","language":"","scoreRank":"","points":""},
{"user":{"rating":"","handle":"filthyrich","country":"United States","countryFlag":"/i/us-flag.png","avatar":""},"registrationDate":"4-5-2021","submissions":"0","language":"","scoreRank":"","points":""},
{"user":{"rating":"","handle":"Sehar98","country":"Pakistan","countryFlag":"/i/pk-flag.png","avatar":""},"registrationDate":"4-5-2021","submissions":"0","language":"","scoreRank":"","points":""},
{"user":{"rating":"","handle":"dinydroid","country":"India","countryFlag":"/i/in-flag.png","avatar":""},"registrationDate":"4-5-2021","submissions":"0","language":"","scoreRank":"","points":""},
{"user":{"rating":"","handle":"mdalamin706688","country":"Bangladesh","countryFlag":"/i/bd-flag.png","avatar":""},"registrationDate":"4-5-2021","submissions":"0","language":"","scoreRank":"","points":""},
{"user":{"rating":"","handle":"akashparua","country":"India","countryFlag":"/i/in-flag.png","avatar":""},"registrationDate":"4-5-2021","submissions":"0","language":"","scoreRank":"","points":""},
{"user":{"rating":"","handle":"Dennoriush","country":"Kenya","countryFlag":"/i/ke-flag.png","avatar":""},"registrationDate":"4-5-2021","submissions":"0","language":"","scoreRank":"","points":""},
{"user":{"rating":"","handle":"Alomgir27","country":"Bangladesh","countryFlag":"/i/bd-flag.png","avatar":""},"registrationDate":"4-5-2021","submissions":"0","language":"","scoreRank":"","points":""},
{"user":{"rating":"","handle":"debasism2014","country":"India","countryFlag":"/i/in-flag.png","avatar":""},"registrationDate":"4-5-2021","submissions":"0","language":"","scoreRank":"","points":""},
{"user":{"rating":"1442","handle":"madbn","country":"Romania","countryFlag":"/i/ro-flag.png","avatar":""},"registrationDate":"4-5-2021","submissions":"0","language":"","scoreRank":"","points":""},
{"user":{"rating":"","handle":"devanshuDesai","country":"United States","countryFlag":"/i/us-flag.png","avatar":""},"registrationDate":"4-5-2021","submissions":"0","language":"","scoreRank":"","points":""},
{"user":{"rating":"","handle":"Mr.Wick07","country":"India","countryFlag":"/i/in-flag.png","avatar":""},"registrationDate":"4-5-2021","submissions":"0","language":"","scoreRank":"","points":""},
{"user":{"rating":"","handle":"omercaylan","country":"Turkey","countryFlag":"/i/tr-flag.png","avatar":""},"registrationDate":"4-5-2021","submissions":"0","language":"","scoreRank":"","points":""},
{"user":{"rating":"","handle":"mblackbourne","country":"United States","countryFlag":"/i/us-flag.png","avatar":""},"registrationDate":"4-5-2021","submissions":"0","language":"","scoreRank":"","points":""},
{"user":{"rating":"","handle":"johanes","country":"Ethiopia","countryFlag":"/i/et-flag.png","avatar":""},"registrationDate":"4-5-2021","submissions":"0","language":"","scoreRank":"","points":""},
{"user":{"rating":"","handle":"Kazim_rizvi","country":"Pakistan","countryFlag":"/i/pk-flag.png","avatar":""},"registrationDate":"4-5-2021","submissions":"0","language":"","scoreRank":"","points":""},
{"user":{"rating":"","handle":"goodm215","country":"United States","countryFlag":"/i/us-flag.png","avatar":""},"registrationDate":"4-5-2021","submissions":"0","language":"","scoreRank":"","points":""},
{"user":{"rating":"","handle":"ash_rick","country":"India","countryFlag":"/i/in-flag.png","avatar":""},"registrationDate":"4-5-2021","submissions":"0","language":"","scoreRank":"","points":""},
{"user":{"rating":"","handle":"het_hoofd","country":"Belgium","countryFlag":"/i/be-flag.png","avatar":""},"registrationDate":"4-5-2021","submissions":"0","language":"","scoreRank":"","points":""},
{"user":{"rating":"","handle":"tiagodfs","country":"Brazil","countryFlag":"/i/br-flag.png","avatar":""},"registrationDate":"4-5-2021","submissions":"0","language":"","scoreRank":"","points":""},
{"user":{"rating":"","handle":"lorenzoflores","country":"United States","countryFlag":"/i/us-flag.png","avatar":""},"registrationDate":"4-5-2021","submissions":"0","language":"","scoreRank":"","points":""},
{"user":{"rating":"","handle":"mnabu55","country":"Japan","countryFlag":"/i/jp-flag.png","avatar":""},"registrationDate":"4-5-2021","submissions":"0","language":"","scoreRank":"","points":""},
{"user":{"rating":"1890","handle":"gardn999","country":"United States","countryFlag":"/i/us-flag.png","avatar":""},"registrationDate":"4-5-2021","submissions":"0","language":"","scoreRank":"","points":""},
{"user":{"rating":"","handle":"mysatellite99","country":"United States","countryFlag":"/i/us-flag.png","avatar":""},"registrationDate":"4-5-2021","submissions":"0","language":"","scoreRank":"","points":""},
{"user":{"rating":"","handle":"sebasmos","country":"Colombia","countryFlag":"/i/co-flag.png","avatar":""},"registrationDate":"4-5-2021","submissions":"0","language":"","scoreRank":"","points":""},
{"user":{"rating":"","handle":"recuraki","country":"Japan","countryFlag":"/i/jp-flag.png","avatar":""},"registrationDate":"4-5-2021","submissions":"0","language":"","scoreRank":"","points":""},
{"user":{"rating":"","handle":"pmn","country":"India","countryFlag":"/i/in-flag.png","avatar":""},"registrationDate":"4-5-2021","submissions":"0","language":"","scoreRank":"","points":""},
{"user":{"rating":"","handle":"mendeza","country":"United States","countryFlag":"/i/us-flag.png","avatar":""},"registrationDate":"4-5-2021","submissions":"0","language":"","scoreRank":"","points":""},
{"user":{"rating":"1362","handle":"number13","country":"Nepal","countryFlag":"/i/np-flag.png","avatar":""},"registrationDate":"4-5-2021","submissions":"459714","language":"","scoreRank":"","points":""},
{"user":{"rating":"0","handle":"solokop","country":"Viet Nam","countryFlag":"/i/vn-flag.png","avatar":"https://topcoder-prod-media.s3.amazonaws.com/member/profile/solokop-1492784870731.jpeg"},"registrationDate":"4-5-2021","submissions":"0","language":"","scoreRank":"","points":""},
{"user":{"rating":"","handle":"rodsan","country":"United States","countryFlag":"/i/us-flag.png","avatar":""},"registrationDate":"4-5-2021","submissions":"0","language":"","scoreRank":"","points":""},
{"user":{"rating":"","handle":"VageeshaDatta","country":"India","countryFlag":"/i/in-flag.png","avatar":""},"registrationDate":"4-5-2021","submissions":"0","language":"","scoreRank":"","points":""},
{"user":{"rating":"","handle":"sbm12","country":"India","countryFlag":"/i/in-flag.png","avatar":""},"registrationDate":"4-5-2021","submissions":"0","language":"","scoreRank":"","points":""},
{"user":{"rating":"","handle":"adityaraj_sahu","country":"India","countryFlag":"/i/in-flag.png","avatar":""},"registrationDate":"4-5-2021","submissions":"0","language":"","scoreRank":"","points":""},
{"user":{"rating":"","handle":"Ben2532g","country":"India","countryFlag":"/i/in-flag.png","avatar":""},"registrationDate":"4-5-2021","submissions":"0","language":"","scoreRank":"","points":""},
{"user":{"rating":"","handle":"adarshrajbhar08","country":"India","countryFlag":"/i/in-flag.png","avatar":""},"registrationDate":"4-6-2021","submissions":"0","language":"","scoreRank":"","points":""},
{"user":{"rating":"","handle":"hsj13","country":"India","countryFlag":"/i/in-flag.png","avatar":""},"registrationDate":"4-6-2021","submissions":"0","language":"","scoreRank":"","points":""},
{"user":{"rating":"","handle":"nikhila101","country":"India","countryFlag":"/i/in-flag.png","avatar":""},"registrationDate":"4-6-2021","submissions":"0","language":"","scoreRank":"","points":""},
{"user":{"rating":"","handle":"RahulG67","country":"India","countryFlag":"/i/in-flag.png","avatar":""},"registrationDate":"4-6-2021","submissions":"0","language":"","scoreRank":"","points":""},
{"user":{"rating":"","handle":"SURAJPRASAD13","country":"India","countryFlag":"/i/in-flag.png","avatar":""},"registrationDate":"4-6-2021","submissions":"0","language":"","scoreRank":"","points":""},
{"user":{"rating":"","handle":"mousamdeyhkn","country":"India","countryFlag":"/i/in-flag.png","avatar":""},"registrationDate":"4-6-2021","submissions":"0","language":"","scoreRank":"","points":""},
{"user":{"rating":"","handle":"2tix","country":"Czech Republic","countryFlag":"/i/cz-flag.png","avatar":""},"registrationDate":"4-6-2021","submissions":"0","language":"","scoreRank":"","points":""},
{"user":{"rating":"","handle":"parthwaidya","country":"India","countryFlag":"/i/in-flag.png","avatar":""},"registrationDate":"4-6-2021","submissions":"0","language":"","scoreRank":"","points":""},
{"user":{"rating":"","handle":"harshaldhone","country":"India","countryFlag":"/i/in-flag.png","avatar":""},"registrationDate":"4-6-2021","submissions":"0","language":"","scoreRank":"","points":""},
{"user":{"rating":"","handle":"ajat31535","country":"India","countryFlag":"/i/in-flag.png","avatar":""},"registrationDate":"4-6-2021","submissions":"0","language":"","scoreRank":"","points":""},
{"user":{"rating":"","handle":"FRGT50","country":"France","countryFlag":"/i/fr-flag.png","avatar":""},"registrationDate":"4-6-2021","submissions":"0","language":"","scoreRank":"","points":""},
{"user":{"rating":"","handle":"rewrite0w0","country":"South Korea","countryFlag":"/i/kr-flag.png","avatar":""},"registrationDate":"4-6-2021","submissions":"0","language":"","scoreRank":"","points":""},
{"user":{"rating":"","handle":"prsa","country":"India","countryFlag":"/i/in-flag.png","avatar":""},"registrationDate":"4-6-2021","submissions":"0","language":"","scoreRank":"","points":""},
{"user":{"rating":"","handle":"vr_2432","country":"India","countryFlag":"/i/in-flag.png","avatar":""},"registrationDate":"4-6-2021","submissions":"0","language":"","scoreRank":"","points":""},
{"user":{"rating":"","handle":"nikhkhnke","country":"India","countryFlag":"/i/in-flag.png","avatar":""},"registrationDate":"4-6-2021","submissions":"0","language":"","scoreRank":"","points":""},
{"user":{"rating":"","handle":"irfanul8karim","country":"Bangladesh","countryFlag":"/i/bd-flag.png","avatar":""},"registrationDate":"4-6-2021","submissions":"0","language":"","scoreRank":"","points":""},
{"user":{"rating":"","handle":"nickooms","country":"Belgium","countryFlag":"/i/be-flag.png","avatar":""},"registrationDate":"4-6-2021","submissions":"0","language":"","scoreRank":"","points":""},
{"user":{"rating":"2042","handle":"JacoCronje","country":"South Africa","countryFlag":"/i/za-flag.png","avatar":"https://www.topcoder.com/i/m/JacoCronje.jpeg"},"registrationDate":"4-6-2021","submissions":"0","language":"","scoreRank":"","points":""},
{"user":{"rating":"","handle":"vgrover21","country":"India","countryFlag":"/i/in-flag.png","avatar":""},"registrationDate":"4-6-2021","submissions":"0","language":"","scoreRank":"","points":""},
{"user":{"rating":"","handle":"yacine_hmy","country":"Algeria","countryFlag":"/i/dz-flag.png","avatar":""},"registrationDate":"4-6-2021","submissions":"0","language":"","scoreRank":"","points":""},
{"user":{"rating":"","handle":"Sasisri","country":"India","countryFlag":"/i/in-flag.png","avatar":""},"registrationDate":"4-6-2021","submissions":"0","language":"","scoreRank":"","points":""},
{"user":{"rating":"","handle":"sup124","country":"India","countryFlag":"/i/in-flag.png","avatar":""},"registrationDate":"4-6-2021","submissions":"0","language":"","scoreRank":"","points":""},
{"user":{"rating":"796","handle":"cichy1024","country":"Poland","countryFlag":"/i/pl-flag.png","avatar":"https://www.topcoder.com/i/m/cichy1024_big.jpg"},"registrationDate":"4-6-2021","submissions":"0","language":"","scoreRank":"","points":""},
{"user":{"rating":"","handle":"bilgee.mlub","country":"Mongolia","countryFlag":"/i/mn-flag.png","avatar":""},"registrationDate":"4-6-2021","submissions":"0","language":"","scoreRank":"","points":""},
{"user":{"rating":"","handle":"chandbashab","country":"India","countryFlag":"/i/in-flag.png","avatar":""},"registrationDate":"4-6-2021","submissions":"0","language":"","scoreRank":"","points":""},
{"user":{"rating":"","handle":"aeclean","country":"Brazil","countryFlag":"/i/br-flag.png","avatar":""},"registrationDate":"4-6-2021","submissions":"0","language":"","scoreRank":"","points":""},
{"user":{"rating":"","handle":"george.williams","country":"United States","countryFlag":"/i/us-flag.png","avatar":""},"registrationDate":"4-6-2021","submissions":"0","language":"","scoreRank":"","points":""},
{"user":{"rating":"","handle":"kanishchugh","country":"India","countryFlag":"/i/in-flag.png","avatar":""},"registrationDate":"4-6-2021","submissions":"0","language":"","scoreRank":"","points":""},
{"user":{"rating":"","handle":"Thomaub","country":"France","countryFlag":"/i/fr-flag.png","avatar":""},"registrationDate":"4-6-2021","submissions":"0","language":"","scoreRank":"","points":""},
{"user":{"rating":"","handle":"tensorgod_","country":"Zambia","countryFlag":"/i/zm-flag.png","avatar":""},"registrationDate":"4-6-2021","submissions":"0","language":"","scoreRank":"","points":""},
{"user":{"rating":"","handle":"abukie969","country":"China","countryFlag":"/i/cn-flag.png","avatar":""},"registrationDate":"4-6-2021","submissions":"0","language":"","scoreRank":"","points":""},
{"user":{"rating":"1433","handle":"kishore_g84","country":"India","countryFlag":"/i/in-flag.png","avatar":""},"registrationDate":"4-6-2021","submissions":"0","language":"","scoreRank":"","points":""},
{"user":{"rating":"","handle":"venkat_s_solasa","country":"India","countryFlag":"/i/in-flag.png","avatar":""},"registrationDate":"4-6-2021","submissions":"0","language":"","scoreRank":"","points":""},
{"user":{"rating":"","handle":"Eshan2001","country":"United States","countryFlag":"/i/us-flag.png","avatar":""},"registrationDate":"4-6-2021","submissions":"0","language":"","scoreRank":"","points":""},
{"user":{"rating":"","handle":"sk4587","country":"India","countryFlag":"/i/in-flag.png","avatar":""},"registrationDate":"4-7-2021","submissions":"0","language":"","scoreRank":"","points":""},
{"user":{"rating":"","handle":"coconan","country":"China","countryFlag":"/i/cn-flag.png","avatar":""},"registrationDate":"4-7-2021","submissions":"0","language":"","scoreRank":"","points":""},
{"user":{"rating":"","handle":"helloworld{123}","country":"India","countryFlag":"/i/in-flag.png","avatar":""},"registrationDate":"4-7-2021","submissions":"0","language":"","scoreRank":"","points":""},
{"user":{"rating":"","handle":"kkishore9891","country":"India","countryFlag":"/i/in-flag.png","avatar":""},"registrationDate":"4-7-2021","submissions":"0","language":"","scoreRank":"","points":""},
{"user":{"rating":"","handle":"im_ani_007","country":"India","countryFlag":"/i/in-flag.png","avatar":""},"registrationDate":"4-7-2021","submissions":"0","language":"","scoreRank":"","points":""},
{"user":{"rating":"","handle":"k.r.shrayas","country":"India","countryFlag":"/i/in-flag.png","avatar":""},"registrationDate":"4-7-2021","submissions":"0","language":"","scoreRank":"","points":""},
{"user":{"rating":"","handle":"amrit.","country":"India","countryFlag":"/i/in-flag.png","avatar":""},"registrationDate":"4-7-2021","submissions":"0","language":"","scoreRank":"","points":""},
{"user":{"rating":"","handle":"shreyas7710","country":"India","countryFlag":"/i/in-flag.png","avatar":""},"registrationDate":"4-7-2021","submissions":"0","language":"","scoreRank":"","points":""},
{"user":{"rating":"","handle":"mattythorne","country":"United Kingdom","countryFlag":"/i/gb-flag.png","avatar":""},"registrationDate":"4-7-2021","submissions":"0","language":"","scoreRank":"","points":""},
{"user":{"rating":"","handle":"ShinNra","country":"Japan","countryFlag":"/i/jp-flag.png","avatar":""},"registrationDate":"4-7-2021","submissions":"0","language":"","scoreRank":"","points":""},
{"user":{"rating":"","handle":"joshua00310","country":"India","countryFlag":"/i/in-flag.png","avatar":""},"registrationDate":"4-7-2021","submissions":"0","language":"","scoreRank":"","points":""},
{"user":{"rating":"","handle":"meirka5","country":"Israel","countryFlag":"/i/il-flag.png","avatar":""},"registrationDate":"4-7-2021","submissions":"0","language":"","scoreRank":"","points":""},
{"user":{"rating":"","handle":"Swati_97","country":"India","countryFlag":"/i/in-flag.png","avatar":""},"registrationDate":"4-7-2021","submissions":"0","language":"","scoreRank":"","points":""},
{"user":{"rating":"","handle":"kompalan","country":"United States","countryFlag":"/i/us-flag.png","avatar":""},"registrationDate":"4-7-2021","submissions":"0","language":"","scoreRank":"","points":""},
{"user":{"rating":"","handle":"rabeya_dolon","country":"Bangladesh","countryFlag":"/i/bd-flag.png","avatar":""},"registrationDate":"4-7-2021","submissions":"0","language":"","scoreRank":"","points":""},
{"user":{"rating":"791","handle":"zizo0003","country":"Egypt","countryFlag":"/i/eg-flag.png","avatar":"https://www.topcoder.com/i/m/zizo0003_big.jpg"},"registrationDate":"4-7-2021","submissions":"0","language":"","scoreRank":"","points":""},
{"user":{"rating":"","handle":"withham","country":"South Korea","countryFlag":"/i/kr-flag.png","avatar":""},"registrationDate":"4-7-2021","submissions":"0","language":"","scoreRank":"","points":""},
{"user":{"rating":"","handle":"tamilarasang101","country":"India","countryFlag":"/i/in-flag.png","avatar":""},"registrationDate":"4-8-2021","submissions":"0","language":"","scoreRank":"","points":""},
{"user":{"rating":"","handle":"ashfaq_03","country":"India","countryFlag":"/i/in-flag.png","avatar":""},"registrationDate":"4-8-2021","submissions":"0","language":"","scoreRank":"","points":""},
{"user":{"rating":"","handle":"ccnuer007","country":"China","countryFlag":"/i/cn-flag.png","avatar":""},"registrationDate":"4-8-2021","submissions":"0","language":"","scoreRank":"","points":""},
{"user":{"rating":"","handle":"OUHRA45","country":"Morocco","countryFlag":"/i/ma-flag.png","avatar":""},"registrationDate":"4-8-2021","submissions":"0","language":"","scoreRank":"","points":""},
{"user":{"rating":"","handle":"chabychab","country":"Zambia","countryFlag":"/i/zm-flag.png","avatar":""},"registrationDate":"4-8-2021","submissions":"0","language":"","scoreRank":"","points":""},
{"user":{"rating":"","handle":"SindhukumariP","country":"India","countryFlag":"/i/in-flag.png","avatar":""},"registrationDate":"4-8-2021","submissions":"0","language":"","scoreRank":"","points":""},
{"user":{"rating":"","handle":"akhatova","country":"France","countryFlag":"/i/fr-flag.png","avatar":""},"registrationDate":"4-8-2021","submissions":"0","language":"","scoreRank":"","points":""},
{"user":{"rating":"","handle":"fly_fly","country":"China","countryFlag":"/i/cn-flag.png","avatar":""},"registrationDate":"4-9-2021","submissions":"0","language":"","scoreRank":"","points":""},
{"user":{"rating":"","handle":"erwansandford","country":"France","countryFlag":"/i/fr-flag.png","avatar":""},"registrationDate":"4-9-2021","submissions":"0","language":"","scoreRank":"","points":""},
{"user":{"rating":"","handle":"nleas","country":"Australia","countryFlag":"/i/au-flag.png","avatar":""},"registrationDate":"4-9-2021","submissions":"0","language":"","scoreRank":"","points":""},
{"user":{"rating":"","handle":"emman_1320","country":"India","countryFlag":"/i/in-flag.png","avatar":""},"registrationDate":"4-9-2021","submissions":"0","language":"","scoreRank":"","points":""},
{"user":{"rating":"829","handle":"ashag","country":"United States","countryFlag":"/i/us-flag.png","avatar":""},"registrationDate":"4-9-2021","submissions":"0","language":"","scoreRank":"","points":""},
{"user":{"rating":"","handle":"ath.io","country":"Greece","countryFlag":"/i/gr-flag.png","avatar":""},"registrationDate":"4-9-2021","submissions":"0","language":"","scoreRank":"","points":""},
{"user":{"rating":"","handle":"Ansary","country":"Bangladesh","countryFlag":"/i/bd-flag.png","avatar":""},"registrationDate":"4-10-2021","submissions":"0","language":"","scoreRank":"","points":""},
{"user":{"rating":"1602","handle":"sorokinv","country":"Russia","countryFlag":"/i/ru-flag.png","avatar":""},"registrationDate":"4-10-2021","submissions":"459065","language":"","scoreRank":"","points":""},
{"user":{"rating":"1019","handle":"luizrrodrigues","country":"Brazil","countryFlag":"/i/br-flag.png","avatar":"https://www.topcoder.com/i/m/luizrrodrigues.jpeg"},"registrationDate":"4-10-2021","submissions":"0","language":"","scoreRank":"","points":""},
{"user":{"rating":"0","handle":"penpo","country":"India","countryFlag":"/i/in-flag.png","avatar":""},"registrationDate":"4-10-2021","submissions":"0","language":"","scoreRank":"","points":""},
{"user":{"rating":"","handle":"Anke1822","country":"India","countryFlag":"/i/in-flag.png","avatar":""},"registrationDate":"4-10-2021","submissions":"0","language":"","scoreRank":"","points":""},
{"user":{"rating":"889","handle":"rickmatter","country":"United States","countryFlag":"/i/us-flag.png","avatar":""},"registrationDate":"4-11-2021","submissions":"0","language":"","scoreRank":"","points":""},
{"user":{"rating":"1152","handle":"mtmiron","country":"United States","countryFlag":"/i/us-flag.png","avatar":""},"registrationDate":"4-11-2021","submissions":"0","language":"","scoreRank":"","points":""},
{"user":{"rating":"","handle":"Astropoint","country":"United Arab Emirates","countryFlag":"/i/ae-flag.png","avatar":""},"registrationDate":"4-11-2021","submissions":"0","language":"","scoreRank":"","points":""},
{"user":{"rating":"","handle":"swathi285931","country":"India","countryFlag":"/i/in-flag.png","avatar":""},"registrationDate":"4-11-2021","submissions":"0","language":"","scoreRank":"","points":""},
{"user":{"rating":"","handle":"km4sh","country":"China","countryFlag":"/i/cn-flag.png","avatar":""},"registrationDate":"4-11-2021","submissions":"0","language":"","scoreRank":"","points":""},
{"user":{"rating":"","handle":"raselmandol","country":"Bangladesh","countryFlag":"/i/bd-flag.png","avatar":""},"registrationDate":"4-12-2021","submissions":"0","language":"","scoreRank":"","points":""},
{"user":{"rating":"","handle":"PythonTamer","country":"Australia","countryFlag":"/i/au-flag.png","avatar":""},"registrationDate":"4-12-2021","submissions":"0","language":"","scoreRank":"","points":""},
{"user":{"rating":"","handle":"vijayabkt1","country":"India","countryFlag":"/i/in-flag.png","avatar":""},"registrationDate":"4-12-2021","submissions":"0","language":"","scoreRank":"","points":""},
{"user":{"rating":"923","handle":"chok68","country":"Spain","countryFlag":"/i/es-flag.png","avatar":"https://topcoder-prod-media.s3.amazonaws.com/member/profile/chok68-1509121459918.png"},"registrationDate":"4-12-2021","submissions":"0","language":"","scoreRank":"","points":""},
{"user":{"rating":"","handle":"haonanz","country":"United States","countryFlag":"/i/us-flag.png","avatar":""},"registrationDate":"4-12-2021","submissions":"0","language":"","scoreRank":"","points":""},
{"user":{"rating":"","handle":"mohitbhardwaj","country":"India","countryFlag":"/i/in-flag.png","avatar":"https://topcoder-prod-media.s3.amazonaws.com/member/profile/mohitbhardwaj-1465400643138.jpeg"},"registrationDate":"4-12-2021","submissions":"0","language":"","scoreRank":"","points":""},
{"user":{"rating":"","handle":"Geo_George","country":"India","countryFlag":"/i/in-flag.png","avatar":""},"registrationDate":"4-13-2021","submissions":"0","language":"","scoreRank":"","points":""},
{"user":{"rating":"","handle":"alfiya_Zi","country":"Russia","countryFlag":"/i/ru-flag.png","avatar":"https://topcoder-prod-media.s3.amazonaws.com/member/profile/alfiya_Zi-1506470453472.jpeg"},"registrationDate":"4-13-2021","submissions":"0","language":"","scoreRank":"","points":""},
{"user":{"rating":"443","handle":"hmehta","country":"India","countryFlag":"/i/in-flag.png","avatar":"https://topcoder-prod-media.s3.amazonaws.com/member/profile/hmehta-1460012668303.jpeg"},"registrationDate":"4-13-2021","submissions":"0","language":"","scoreRank":"","points":""},
{"user":{"rating":"","handle":"therealchainman","country":"United States","countryFlag":"/i/us-flag.png","avatar":""},"registrationDate":"4-14-2021","submissions":"0","language":"","scoreRank":"","points":""},
{"user":{"rating":"","handle":"thewires2","country":"India","countryFlag":"/i/in-flag.png","avatar":""},"registrationDate":"4-14-2021","submissions":"0","language":"","scoreRank":"","points":""},
{"user":{"rating":"","handle":"aleka","country":"Singapore","countryFlag":"/i/sg-flag.png","avatar":""},"registrationDate":"4-14-2021","submissions":"0","language":"","scoreRank":"","points":""},
{"user":{"rating":"","handle":"_HarshilShah_","country":"India","countryFlag":"/i/in-flag.png","avatar":""},"registrationDate":"4-14-2021","submissions":"0","language":"","scoreRank":"","points":""},
{"user":{"rating":"","handle":"dzinovev","country":"Russia","countryFlag":"/i/ru-flag.png","avatar":""},"registrationDate":"4-14-2021","submissions":"0","language":"","scoreRank":"","points":""},
{"user":{"rating":"","handle":"briannat","country":"United States","countryFlag":"/i/us-flag.png","avatar":""},"registrationDate":"4-14-2021","submissions":"0","language":"","scoreRank":"","points":""},
{"user":{"rating":"","handle":"dimpitauri","country":"Georgia","countryFlag":"/i/ge-flag.png","avatar":""},"registrationDate":"4-14-2021","submissions":"0","language":"","scoreRank":"","points":""},
{"user":{"rating":"1047","handle":"abelalem","country":"Ethiopia","countryFlag":"/i/et-flag.png","avatar":""},"registrationDate":"4-15-2021","submissions":"0","language":"","scoreRank":"","points":""},
{"user":{"rating":"","handle":"RobaBobBob","country":"India","countryFlag":"/i/in-flag.png","avatar":""},"registrationDate":"4-15-2021","submissions":"0","language":"","scoreRank":"","points":""},
{"user":{"rating":"","handle":"M9M","country":"India","countryFlag":"/i/in-flag.png","avatar":""},"registrationDate":"4-15-2021","submissions":"0","language":"","scoreRank":"","points":""},
{"user":{"rating":"","handle":"khkim2020","country":"United States","countryFlag":"/i/us-flag.png","avatar":""},"registrationDate":"4-15-2021","submissions":"0","language":"","scoreRank":"","points":""},
{"user":{"rating":"","handle":"pantmayank","country":"India","countryFlag":"/i/in-flag.png","avatar":""},"registrationDate":"4-15-2021","submissions":"0","language":"","scoreRank":"","points":""},
{"user":{"rating":"0","handle":"rajrkrish","country":"India","countryFlag":"/i/in-flag.png","avatar":""},"registrationDate":"4-16-2021","submissions":"0","language":"","scoreRank":"","points":""},
{"user":{"rating":"","handle":"beeallucanbee","country":"United States","countryFlag":"/i/us-flag.png","avatar":""},"registrationDate":"4-16-2021","submissions":"0","language":"","scoreRank":"","points":""},
{"user":{"rating":"","handle":"pruthvi_raju","country":"India","countryFlag":"/i/in-flag.png","avatar":""},"registrationDate":"4-16-2021","submissions":"0","language":"","scoreRank":"","points":""},
{"user":{"rating":"","handle":"lucy00","country":"United States","countryFlag":"/i/us-flag.png","avatar":""},"registrationDate":"4-17-2021","submissions":"0","language":"","scoreRank":"","points":""},
{"user":{"rating":"","handle":"ramdani05122000","country":"Indonesia","countryFlag":"/i/id-flag.png","avatar":""},"registrationDate":"4-17-2021","submissions":"0","language":"","scoreRank":"","points":""},
{"user":{"rating":"","handle":"sunny_12","country":"India","countryFlag":"/i/in-flag.png","avatar":""},"registrationDate":"4-18-2021","submissions":"0","language":"","scoreRank":"","points":""},
{"user":{"rating":"","handle":"p1yu5h","country":"India","countryFlag":"/i/in-flag.png","avatar":""},"registrationDate":"4-18-2021","submissions":"0","language":"","scoreRank":"","points":""},
{"user":{"rating":"","handle":"pstreck","country":"United States","countryFlag":"/i/us-flag.png","avatar":""},"registrationDate":"4-18-2021","submissions":"0","language":"","scoreRank":"","points":""},
{"user":{"rating":"913","handle":"PhysBrain","country":"United States","countryFlag":"/i/us-flag.png","avatar":""},"registrationDate":"4-19-2021","submissions":"0","language":"","scoreRank":"","points":""},
{"user":{"rating":"","handle":"Mac13","country":"India","countryFlag":"/i/in-flag.png","avatar":""},"registrationDate":"4-19-2021","submissions":"0","language":"","scoreRank":"","points":""},
{"user":{"rating":"","handle":"Prachi12","country":"India","countryFlag":"/i/in-flag.png","avatar":""},"registrationDate":"4-19-2021","submissions":"0","language":"","scoreRank":"","points":""},
{"user":{"rating":"","handle":"KuldipShejul","country":"India","countryFlag":"/i/in-flag.png","avatar":""},"registrationDate":"4-20-2021","submissions":"0","language":"","scoreRank":"","points":""},
{"user":{"rating":"","handle":"srinivasaenergy","country":"India","countryFlag":"/i/in-flag.png","avatar":""},"registrationDate":"4-20-2021","submissions":"0","language":"","scoreRank":"","points":""},
{"user":{"rating":"1096","handle":"datomi","country":"Russia","countryFlag":"/i/ru-flag.png","avatar":""},"registrationDate":"4-20-2021","submissions":"0","language":"","scoreRank":"","points":""},
{"user":{"rating":"1051","handle":"marcocastangia","country":"Italy","countryFlag":"/i/it-flag.png","avatar":""},"registrationDate":"4-21-2021","submissions":"0","language":"","scoreRank":"","points":""},
{"user":{"rating":"","handle":"obog","country":"Russia","countryFlag":"/i/ru-flag.png","avatar":""},"registrationDate":"4-21-2021","submissions":"0","language":"","scoreRank":"","points":""},
{"user":{"rating":"","handle":"_ryon","country":"United States","countryFlag":"/i/us-flag.png","avatar":""},"registrationDate":"4-21-2021","submissions":"0","language":"","scoreRank":"","points":""},
{"user":{"rating":"","handle":"ankita223","country":"India","countryFlag":"/i/in-flag.png","avatar":""},"registrationDate":"4-21-2021","submissions":"0","language":"","scoreRank":"","points":""},
{"user":{"rating":"","handle":"VishalBarman","country":"India","countryFlag":"/i/in-flag.png","avatar":""},"registrationDate":"4-21-2021","submissions":"0","language":"","scoreRank":"","points":""}]
